describe_json/__init__.py
tests/__init__.py
tests/test_describe_json.py
describe_json-0.1.7.dist-info/AUTHORS.rst
describe_json-0.1.7.dist-info/LICENSE
describe_json-0.1.7.dist-info/METADATA
describe_json-0.1.7.dist-info/WHEEL
describe_json-0.1.7.dist-info/entry_points.txt
describe_json-0.1.7.dist-info/top_level.txt
describe_json-0.1.7.dist-info/RECORD
