Metadata-Version: 2.1
Name: describe-json
Version: 0.1.7
Summary: Tired of looking at JSON objects that contain long arrays? Fear no more!
Home-page: https://github.com/vladiibine/describe_json
Author: Vlad-George Ardelean
Author-email: vlad.george.ardelean@gmail.com
License: MIT license
Keywords: describe_json
Platform: UNKNOWN
Classifier: Development Status :: 2 - Pre-Alpha
Classifier: Intended Audience :: Developers
Classifier: License :: OSI Approved :: MIT License
Classifier: Natural Language :: English
Classifier: Programming Language :: Python :: 2
Classifier: Programming Language :: Python :: 2.7
Classifier: Programming Language :: Python :: 3
Classifier: Programming Language :: Python :: 3.4
Classifier: Programming Language :: Python :: 3.5
Classifier: Programming Language :: Python :: 3.6
Classifier: Programming Language :: Python :: 3.7
